ComponentCalc/__init__.py
ComponentCalc/cli.py
componentcalc-0.0.0.dist-info/licenses/LICENSE
componentcalc-0.0.0.dist-info/METADATA
componentcalc-0.0.0.dist-info/WHEEL
componentcalc-0.0.0.dist-info/entry_points.txt
componentcalc-0.0.0.dist-info/top_level.txt
componentcalc-0.0.0.dist-info/RECORD
