Metadata-Version: 2.4
Name: ComponentCalc
Version: 0.0.0
Summary: An Electrical Engineering calculator suite 
Author-email: Adam Exley <34522460+AdamExley@users.noreply.github.com>
License-Expression: Apache-2.0
Project-URL: Repository, https://github.com/AdamExley/ComponentCalc/
Keywords: electronics,engineering,calculator,circuit,electrical,Electrical Engineering,design
Classifier: Development Status :: 1 - Planning
Classifier: Intended Audience :: End Users/Desktop
Classifier: Intended Audience :: Science/Research
Classifier: Topic :: Scientific/Engineering
Classifier: Topic :: Scientific/Engineering :: Electronic Design Automation (EDA)
Classifier: Operating System :: OS Independent
Classifier: Programming Language :: Python :: 3 :: Only
Requires-Python: >=3.13
License-File: LICENSE
Dynamic: license-file
